<?xml version="1.0" encoding="UTF-8" standalone="yes"?>
<unit xmlns="http://www.srcML.org/srcML/src" xmlns:cpp="http://www.srcML.org/srcML/cpp" revision="1.0.0" language="C++" filename="C:\Users\DRACO\PycharmProjects\Data-Science-Term-Project-1\data\leetcode_cpp\raw\69A-YoungPhysicist.cpp"><cpp:include>#<cpp:directive>include</cpp:directive> <cpp:file>&lt;cstdio&gt;</cpp:file></cpp:include>

<function><type><name>int</name></type> <name>main</name><parameter_list>()</parameter_list><block>{<block_content>
    <decl_stmt><decl><type><name>int</name></type> <name><name>force</name><index>[<expr><literal type="number">3</literal></expr>]</index></name> <init>= <expr><block>{<expr><literal type="number">0</literal></expr>}</block></expr></init></decl>;</decl_stmt> <decl_stmt><decl><type><name>int</name></type> <name>temp</name> <init>= <expr><literal type="number">0</literal></expr></init></decl>;</decl_stmt>
    <decl_stmt><decl><type><name>int</name></type> <name>numVectors</name></decl>;</decl_stmt> <expr_stmt><expr><call><name>scanf</name><argument_list>(<argument><expr><literal type="string">"%d"</literal></expr></argument>, <argument><expr><operator>&amp;</operator><name>numVectors</name></expr></argument>)</argument_list></call></expr>;</expr_stmt>
    <for>for<control>(<init><decl><type><name>int</name></type> <name>k</name> <init>= <expr><literal type="number">0</literal></expr></init></decl>;</init> <condition><expr><name>k</name> <operator>&lt;</operator> <literal type="number">3</literal><operator>*</operator><name>numVectors</name></expr>;</condition> <incr><expr><name>k</name><operator>++</operator></expr></incr>)</control><block>{<block_content><expr_stmt><expr><call><name>scanf</name><argument_list>(<argument><expr><literal type="string">"%d"</literal></expr></argument>, <argument><expr><operator>&amp;</operator><name>temp</name></expr></argument>)</argument_list></call></expr>;</expr_stmt> <expr_stmt><expr><name><name>force</name><index>[<expr><name>k</name><operator>%</operator><literal type="number">3</literal></expr>]</index></name> <operator>+=</operator> <name>temp</name></expr>;</expr_stmt></block_content>}</block></for>
    <expr_stmt><expr><ternary><condition><expr><operator>(</operator><name><name>force</name><index>[<expr><literal type="number">0</literal></expr>]</index></name> <operator>||</operator> <name><name>force</name><index>[<expr><literal type="number">1</literal></expr>]</index></name> <operator>||</operator> <name><name>force</name><index>[<expr><literal type="number">2</literal></expr>]</index></name><operator>)</operator></expr> ?</condition><then> <expr><call><name>printf</name><argument_list>(<argument><expr><literal type="string">"NO"</literal></expr></argument>)</argument_list></call></expr> </then><else>: <expr><call><name>printf</name><argument_list>(<argument><expr><literal type="string">"YES"</literal></expr></argument>)</argument_list></call></expr></else></ternary></expr>;</expr_stmt>
    <return>return <expr><literal type="number">0</literal></expr>;</return>
</block_content>}</block></function>
</unit>
